prefixed_identity_field/__init__.py
prefixed_identity_field/exceptions.py
prefixed_identity_field/fields.py
prefixed_identity_field/uuid_utils.py
django_prefixed_identity_field-1.2.0.dist-info/METADATA
django_prefixed_identity_field-1.2.0.dist-info/WHEEL
django_prefixed_identity_field-1.2.0.dist-info/RECORD
